jupyterlab_twitch/__init__.py
jupyterlab_twitch/_version.py
jupyterlab_twitch/twitch_player.py
jupyterlab_twitch/labextension/package.json
jupyterlab_twitch/labextension/static/448.7e6a7100f5ff873010ae.js
jupyterlab_twitch/labextension/static/480.763dcf10c5a70dc89e8f.js
jupyterlab_twitch/labextension/static/534.d97b6287648abce95e06.js
jupyterlab_twitch/labextension/static/534.d97b6287648abce95e06.js.LICENSE.txt
jupyterlab_twitch/labextension/static/568.429a4fe446adecedb09d.js
jupyterlab_twitch/labextension/static/625.ce1d7b8c07c317c1b1c8.js
jupyterlab_twitch/labextension/static/625.ce1d7b8c07c317c1b1c8.js.LICENSE.txt
jupyterlab_twitch/labextension/static/remoteEntry.1f2be740711ea503dd99.js
jupyterlab_twitch/labextension/static/style.js
jupyterlab_twitch-0.2.0.data/data/share/jupyter/labextensions/@data-exp-lab/jupyterlab-twitch/install.json
jupyterlab_twitch-0.2.0.data/data/share/jupyter/labextensions/@data-exp-lab/jupyterlab-twitch/package.json
jupyterlab_twitch-0.2.0.data/data/share/jupyter/labextensions/@data-exp-lab/jupyterlab-twitch/static/448.7e6a7100f5ff873010ae.js
jupyterlab_twitch-0.2.0.data/data/share/jupyter/labextensions/@data-exp-lab/jupyterlab-twitch/static/480.763dcf10c5a70dc89e8f.js
jupyterlab_twitch-0.2.0.data/data/share/jupyter/labextensions/@data-exp-lab/jupyterlab-twitch/static/534.d97b6287648abce95e06.js
jupyterlab_twitch-0.2.0.data/data/share/jupyter/labextensions/@data-exp-lab/jupyterlab-twitch/static/534.d97b6287648abce95e06.js.LICENSE.txt
jupyterlab_twitch-0.2.0.data/data/share/jupyter/labextensions/@data-exp-lab/jupyterlab-twitch/static/568.429a4fe446adecedb09d.js
jupyterlab_twitch-0.2.0.data/data/share/jupyter/labextensions/@data-exp-lab/jupyterlab-twitch/static/625.ce1d7b8c07c317c1b1c8.js
jupyterlab_twitch-0.2.0.data/data/share/jupyter/labextensions/@data-exp-lab/jupyterlab-twitch/static/625.ce1d7b8c07c317c1b1c8.js.LICENSE.txt
jupyterlab_twitch-0.2.0.dist-info/LICENSE
jupyterlab_twitch-0.2.0.dist-info/METADATA
jupyterlab_twitch-0.2.0.dist-info/WHEEL
jupyterlab_twitch-0.2.0.dist-info/top_level.txt
jupyterlab_twitch-0.2.0.dist-info/RECORD
